Metadata-Version: 1.0
Name: who-i
Version: 0.5
Summary: this about test4
Home-page: UNKNOWN
Author: UNKNOWN
Author-email: UNKNOWN
License: UNKNOWN
Platform: UNKNOWN
